logmap/__init__.py
logmap/imports.py
logmap/logmap.py
logmap/yapmap.py
logmap-0.0.3.dist-info/LICENSE
logmap-0.0.3.dist-info/METADATA
logmap-0.0.3.dist-info/WHEEL
logmap-0.0.3.dist-info/top_level.txt
logmap-0.0.3.dist-info/RECORD
