Metadata-Version: 2.1
Name: logmap
Version: 0.0.3
Summary: A hierarchical, context-manager logger utility with multiprocess mapping capabilities
Home-page: https://github.com/Princeton-CDH/ppa-nlp
Author: Ryan Heuser
Author-email: ryan.heuser@princeton.edu
License: GNU General Public License v3
Project-URL: Project Home, https://cdh.princeton.edu/
Project-URL: Bug Tracker, https://github.com/Princeton-CDH/ppa-nlp/issues
Classifier: Development Status :: 2 - Pre-Alpha
Classifier: Programming Language :: Python :: 3
Classifier: Intended Audience :: Developers
Classifier: License :: OSI Approved :: Apache Software License
Classifier: Operating System :: OS Independent
Classifier: Topic :: Software Development :: Libraries :: Python Modules
Requires-Python: >=3.6
License-File: LICENSE
Requires-Dist: loguru
Requires-Dist: humanfriendly
Requires-Dist: tqdm
Requires-Dist: multiprocess
Provides-Extra: all
Requires-Dist: tox ; extra == 'all'
Requires-Dist: sphinx ; extra == 'all'
Requires-Dist: twine ; extra == 'all'
Requires-Dist: wheel ; extra == 'all'
Requires-Dist: pytest-cov ; extra == 'all'
Requires-Dist: pytest >=7.2 ; extra == 'all'
Requires-Dist: pytest-ordering ; extra == 'all'
Provides-Extra: dev
Requires-Dist: tox ; extra == 'dev'
Requires-Dist: sphinx ; extra == 'dev'
Requires-Dist: twine ; extra == 'dev'
Requires-Dist: wheel ; extra == 'dev'
Requires-Dist: pytest-cov ; extra == 'dev'
Provides-Extra: test
Requires-Dist: pytest >=7.2 ; extra == 'test'
Requires-Dist: pytest-ordering ; extra == 'test'
